decentriq_platform/5.root.json
decentriq_platform/__init__.py
decentriq_platform/ab_media/__init__.py
decentriq_platform/ab_media/ab_media.py
decentriq_platform/ab_media/advertiser_api.py
decentriq_platform/ab_media/advertiser_computations.py
decentriq_platform/ab_media/audience_definitions.py
decentriq_platform/ab_media/audience_statistics_definition.py
decentriq_platform/ab_media/builder.py
decentriq_platform/ab_media/computations.py
decentriq_platform/ab_media/features.py
decentriq_platform/ab_media/helper.py
decentriq_platform/ab_media/lookalike_audience_builder.py
decentriq_platform/ab_media/publisher_api.py
decentriq_platform/ab_media/publisher_computations.py
decentriq_platform/ab_media/request.py
decentriq_platform/ab_media/rule_based_builder.py
decentriq_platform/ab_media/tests/test_helper.py
decentriq_platform/ab_media/version.py
decentriq_platform/analytics/__init__.py
decentriq_platform/analytics/analytics_dcr.py
decentriq_platform/analytics/builder.py
decentriq_platform/analytics/dataset_sink_compute_nodes.py
decentriq_platform/analytics/existing_builder.py
decentriq_platform/analytics/high_level_node.py
decentriq_platform/analytics/matching_compute_nodes.py
decentriq_platform/analytics/node_definitions.py
decentriq_platform/analytics/preview_compute_nodes.py
decentriq_platform/analytics/python_compute_nodes.py
decentriq_platform/analytics/python_environment_compute_nodes.py
decentriq_platform/analytics/r_compute_nodes.py
decentriq_platform/analytics/raw_data_nodes.py
decentriq_platform/analytics/s3_sink_compute_nodes.py
decentriq_platform/analytics/script.py
decentriq_platform/analytics/sql_compute_nodes.py
decentriq_platform/analytics/sql_helper.py
decentriq_platform/analytics/sqlite_compute_nodes.py
decentriq_platform/analytics/synthetic_compute_nodes.py
decentriq_platform/analytics/table_data_nodes.py
decentriq_platform/analytics/version.py
decentriq_platform/api.py
decentriq_platform/archv2/__init__.py
decentriq_platform/archv2/client.py
decentriq_platform-0.39.2.dist-info/METADATA
decentriq_platform-0.39.2.dist-info/WHEEL
decentriq_platform-0.39.2.dist-info/RECORD
