Metadata-Version: 2.4
Name: decentriq-platform
Version: 0.39.2
Summary: Python client library for the Decentriq platform
Author: decentriq
Author-email: opensource@decentriq.com
Requires-Python: >=3.9, !=2.7.*, !=3.0.*, !=3.1.*, !=3.2.*, !=3.3.*, !=3.4.*, !=3.5.*, !=3.6.*, !=3.7.*, !=3.8.*
Classifier: Programming Language :: Python :: 3
Classifier: Programming Language :: Python :: 3.10
Classifier: Programming Language :: Python :: 3.11
Classifier: Programming Language :: Python :: 3.12
Classifier: Programming Language :: Python :: 3.13
Classifier: Programming Language :: Python :: 3.14
Requires-Dist: asn1crypto (>=1.5.1,<2.0.0)
Requires-Dist: cbor2 (>=5.4.6,<6.0.0)
Requires-Dist: chily (>=0.9.0,<0.10.0)
Requires-Dist: cryptography (>=44.0.1,<45.0.0)
Requires-Dist: decentriq-dcr-compiler (==0.19.10)
Requires-Dist: decentriq-transparency-verification (==0.2.0)
Requires-Dist: ecdsa (>=0.18.0,<0.19.0)
Requires-Dist: idna (>=3.7,<4.0)
Requires-Dist: pem (>=21.2.0,<22.0.0)
Requires-Dist: protobuf (>=5.29.5,<6.0.0)
Requires-Dist: pyOpenSSL (>=24.0.0,<25.0.0)
Requires-Dist: requests (>=2.32.4,<3.0.0)
Requires-Dist: sgx-ias-structs (>=0.2.0,<0.3.0)
Requires-Dist: typing-extensions (>=4.12.0,<5.0.0)
Requires-Dist: urllib3 (==1.26.19)
Project-URL: Homepage, https://github.com/decentriq/decentriq-platform
Project-URL: Repository, https://github.com/decentriq/decentriq-platform
